layersdk/__init__.py
layersdk-0.0.1.dist-info/LICENSE
layersdk-0.0.1.dist-info/METADATA
layersdk-0.0.1.dist-info/WHEEL
layersdk-0.0.1.dist-info/top_level.txt
layersdk-0.0.1.dist-info/RECORD
